VisCPM/__init__.py
VisCPM/viscpm_chat.py
VisCPM/viscpm_paint.py
VisCPM/cpm_tokenizers/__init__.py
VisCPM/cpm_tokenizers/bee.py
VisCPM/cpm_tokenizers/vocabs/bee.txt
VisCPM/generation/__init__.py
VisCPM/generation/generation_utils.py
VisCPM/generation/vllm_bee.py
VisCPM/models/__init__.py
VisCPM/models/beit3.py
VisCPM/models/cpmbee.py
VisCPM/models/modeling_utils.py
VisCPM/models/stablediffusion.py
VisCPM/models/vlg_cpmbee.py
VisCPM/models/vlu_cpmbee.py
VisCPM/models/modules/__init__.py
VisCPM/models/modules/attention.py
VisCPM/models/modules/blocks.py
VisCPM/models/modules/config.py
VisCPM/models/modules/embedding.py
VisCPM/models/modules/feedforward.py
VisCPM/models/modules/layernorm.py
VisCPM/models/modules/linear.py
VisCPM/models/modules/position_embedding.py
VisCPM/models/modules/transformer.py
VisCPM/utils/__init__.py
VisCPM/utils/utils.py
VisCPM-0.0.1.dev0.dist-info/METADATA
VisCPM-0.0.1.dev0.dist-info/WHEEL
VisCPM-0.0.1.dev0.dist-info/top_level.txt
VisCPM-0.0.1.dev0.dist-info/RECORD
